ironxl-2025.12.0.3.data/data/IronXLNet/Azure.Core.dll
ironxl-2025.12.0.3.data/data/IronXLNet/Azure.Data.Tables.dll
ironxl-2025.12.0.3.data/data/IronXLNet/Babel.Licensing.dll
ironxl-2025.12.0.3.data/data/IronXLNet/BitMiracle.LibTiff.NET.dll
ironxl-2025.12.0.3.data/data/IronXLNet/BouncyCastle.Cryptography.dll
ironxl-2025.12.0.3.data/data/IronXLNet/CsvHelper.dll
ironxl-2025.12.0.3.data/data/IronXLNet/DeviceId.dll
ironxl-2025.12.0.3.data/data/IronXLNet/Enums.NET.dll
ironxl-2025.12.0.3.data/data/IronXLNet/ExtendedNumerics.BigDecimal.dll
ironxl-2025.12.0.3.data/data/IronXLNet/Google.Protobuf.dll
ironxl-2025.12.0.3.data/data/IronXLNet/Grpc.Core.Api.dll
ironxl-2025.12.0.3.data/data/IronXLNet/Grpc.Net.Client.dll
ironxl-2025.12.0.3.data/data/IronXLNet/Grpc.Net.Common.dll
ironxl-2025.12.0.3.data/data/IronXLNet/ICSharpCode.SharpZipLib.dll
ironxl-2025.12.0.3.data/data/IronXLNet/IronSoftware.Drawing.Abstractions.dll
ironxl-2025.12.0.3.data/data/IronXLNet/IronSoftware.Drawing.Common.dll
ironxl-2025.12.0.3.data/data/IronXLNet/IronSoftware.Logger.dll
ironxl-2025.12.0.3.data/data/IronXLNet/IronSoftware.Shared.dll
ironxl-2025.12.0.3.data/data/IronXLNet/IronXL.dll
ironxl-2025.12.0.3.data/data/IronXLNet/IronXL.xml
ironxl-2025.12.0.3.data/data/IronXLNet/MathNet.Numerics.dll
ironxl-2025.12.0.3.data/data/IronXLNet/Microsoft.Bcl.AsyncInterfaces.dll
ironxl-2025.12.0.3.data/data/IronXLNet/Microsoft.Bcl.TimeProvider.dll
ironxl-2025.12.0.3.data/data/IronXLNet/Microsoft.Extensions.Configuration.Abstractions.dll
ironxl-2025.12.0.3.data/data/IronXLNet/Microsoft.Extensions.Configuration.Binder.dll
ironxl-2025.12.0.3.data/data/IronXLNet/Microsoft.Extensions.Configuration.FileExtensions.dll
ironxl-2025.12.0.3.data/data/IronXLNet/Microsoft.Extensions.Configuration.Json.dll
ironxl-2025.12.0.3.data/data/IronXLNet/Microsoft.Extensions.Configuration.dll
ironxl-2025.12.0.3.data/data/IronXLNet/Microsoft.Extensions.FileProviders.Abstractions.dll
ironxl-2025.12.0.3.dist-info/METADATA
ironxl-2025.12.0.3.dist-info/WHEEL
ironxl-2025.12.0.3.dist-info/top_level.txt
ironxl-2025.12.0.3.dist-info/RECORD
