Metadata-Version: 2.1
Name: IronXL
Version: 2025.12.0.3
Summary: IronXL for Python
Home-page: https://ironxl.com/
Author: Iron Software
Author-email: developers@ironsoftware.com
License: Commercial
Platform: UNKNOWN
Classifier: Development Status :: 5 - Production/Stable
Classifier: Intended Audience :: Developers
Classifier: Operating System :: OS Independent
Classifier: Operating System :: Microsoft :: Windows
Classifier: Operating System :: MacOS
Classifier: Operating System :: POSIX :: Linux
Classifier: Programming Language :: Python :: 3.7
Classifier: Programming Language :: Python :: 3.8
Classifier: Programming Language :: Python :: 3.9
Classifier: Programming Language :: Python :: 3.10
Classifier: Programming Language :: Python :: 3.11
Classifier: Programming Language :: Python :: 3.12
Classifier: Topic :: Adaptive Technologies
Classifier: Topic :: Artistic Software
Classifier: Topic :: Communications
Classifier: Topic :: Database
Classifier: Topic :: Desktop Environment
Classifier: Topic :: Documentation
Classifier: Topic :: Education
Classifier: Topic :: File Formats
Classifier: Topic :: Games/Entertainment
Classifier: Topic :: Internet
Classifier: Topic :: Multimedia
Classifier: Topic :: Office/Business
Classifier: Topic :: Printing
Classifier: Topic :: Scientific/Engineering
Classifier: Topic :: Security
Classifier: Topic :: Software Development
Classifier: Topic :: System
Classifier: Topic :: Text Processing
Classifier: Topic :: Utilities
Requires-Python: >=3.7, <4
Requires-Dist: pythonnet
